forecastblurdenoise/DeepGP.py
forecastblurdenoise/__init__.py
forecastblurdenoise/data_loader.py
forecastblurdenoise/dataformatter.py
forecastblurdenoise/forecast_blur_denoise.py
forecastblurdenoise/main.py
forecastblurdenoise/train_forecast_blur_denoise.py
forecastblurdenoise/forecasting_models/__init__.py
forecastblurdenoise/forecasting_models/autoformer.py
forecastblurdenoise/modules/__init__.py
forecastblurdenoise/modules/decoder.py
forecastblurdenoise/modules/encoder.py
forecastblurdenoise/modules/encoding.py
forecastblurdenoise/modules/feedforward.py
forecastblurdenoise/modules/multi_head_attention.py
forecastblurdenoise/modules/transformer.py
forecastblurdenoise-1.0.7.dist-info/LICENSE
forecastblurdenoise-1.0.7.dist-info/METADATA
forecastblurdenoise-1.0.7.dist-info/WHEEL
forecastblurdenoise-1.0.7.dist-info/entry_points.txt
forecastblurdenoise-1.0.7.dist-info/top_level.txt
forecastblurdenoise-1.0.7.dist-info/RECORD
