Metadata-Version: 2.1
Name: forecastblurdenoise
Version: 1.0.7
Summary: UNKNOWN
Home-page: https://github.com/SepKfr/Fine_grained_forecasting
Author: Sepideh Koohfar
Author-email: sepideh.koohfar@unh.edu
License: MIT
Platform: UNKNOWN
Classifier: Programming Language :: Python :: 3
Classifier: Programming Language :: Python :: 3.9
Classifier: License :: OSI Approved :: MIT License
Classifier: Operating System :: OS Independent
Classifier: Topic :: Scientific/Engineering :: Artificial Intelligence
Requires-Python: >=3.9
License-File: LICENSE
Requires-Dist: gpytorch (>=1.9.0)
Requires-Dist: torch (>=2.0.1)
Requires-Dist: pandas (>=1.5.2)
Requires-Dist: numpy (>=1.23.5)
Requires-Dist: optuna (>=3.3.0)
